MANIFEST.in
README.rst
requirements-test.txt
requirements.txt
setup.cfg
setup.py
sacrud/__init__.py
sacrud/action.py
sacrud/common.py
sacrud/preprocessing.py
sacrud.egg-info/PKG-INFO
sacrud.egg-info/SOURCES.txt
sacrud.egg-info/dependency_links.txt
sacrud.egg-info/not-zip-safe
sacrud.egg-info/pbr.json
sacrud.egg-info/requires.txt
sacrud.egg-info/top_level.txt
tests/__init__.py
tests/test_action.py
tests/test_common.py
tests/test_preprocessor.py
tests/test_sessionmaker.py